generic_decorators/__init__.py
generic_decorators/generic_decorators.py
generic_decorators-1.0.3.dist-info/LICENSE
generic_decorators-1.0.3.dist-info/METADATA
generic_decorators-1.0.3.dist-info/WHEEL
generic_decorators-1.0.3.dist-info/top_level.txt
generic_decorators-1.0.3.dist-info/RECORD
