Metadata-Version: 2.1
Name: generic-decorators
Version: 1.0.3
Summary: Generic Python Decorators for use in any project
Home-page: https://github.com/DamZiobro/generic-decorators
Author: Damian Ziobro
Author-email: damian@xmementoit.com
License: MIT
Platform: UNKNOWN
Classifier: License :: OSI Approved :: MIT License
Classifier: Programming Language :: Python :: 3
Requires-Python: >=3.0
Requires-Dist: joblib (>=1.0.1)
